trddt/__init__.py
trddt/krx.py
trddt-0.3.2.dist-info/LICENSE
trddt-0.3.2.dist-info/METADATA
trddt-0.3.2.dist-info/WHEEL
trddt-0.3.2.dist-info/top_level.txt
trddt-0.3.2.dist-info/RECORD
