Metadata-Version: 2.1
Name: trddt
Version: 0.3.2
Summary: 한국거래소 기준 Datetime Functions 패키지
Home-page: https://github.com/innovata/TradeDatetime
Author: innovata
Author-email: iinnovata@gmail.com
Classifier: Programming Language :: Python :: 3
Classifier: License :: OSI Approved :: MIT License
Classifier: Operating System :: OS Independent
Requires-Python: >=3.8
License-File: LICENSE
Requires-Dist: ipylib
Requires-Dist: holidays
Requires-Dist: pandas
Requires-Dist: xlrd
Requires-Dist: openpyxl
Requires-Dist: requests
